samplelib2/__init__.py
samplelib2/samplelib2.py
samplelib2-0.0.3.dist-info/METADATA
samplelib2-0.0.3.dist-info/WHEEL
samplelib2-0.0.3.dist-info/top_level.txt
samplelib2-0.0.3.dist-info/RECORD
