Metadata-Version: 2.1
Name: samplelib2
Version: 0.0.3
Requires-Dist: samplelib1
